MANIFEST.in
README.md
pyproject.toml
setup.cfg
setup.py
/home/dsuo/src/mujoco-py-derivatives/mujoco_py_derivatives/cymjd.c
/home/dsuo/src/mujoco-py-derivatives/mujoco_py_derivatives/mujoco_derivatives_struct.c
mujoco_py_derivatives/cymjd.c
mujoco_py_derivatives/cymjd.pyx
mujoco_py_derivatives/mujoco_derivatives_struct.c
mujoco_py_derivatives/mujoco_derivatives_struct.h
mujoco_py_derivatives/mujoco_py_derivatives.c
mujoco_py_derivatives.egg-info/PKG-INFO
mujoco_py_derivatives.egg-info/SOURCES.txt
mujoco_py_derivatives.egg-info/dependency_links.txt
mujoco_py_derivatives.egg-info/requires.txt
mujoco_py_derivatives.egg-info/top_level.txt
mujoco_py_derivatives/pxd/cmujoco_jacobian_struct.pxd