Metadata-Version: 2.1
Name: mujoco-py-derivatives
Version: 0.1.4
Summary: Derivatives for MuJoCo
Home-page: https://github.com/MinRegret/mujoco-py-derivatives
Author: Daniel Suo
Author-email: danielsuo@gmail.com
License: MIT
Keywords: mujoco mujoco_py derivatives
Platform: UNKNOWN
